{
    "tableName": "SubModule Table",
    "tableHeaders": [
        {
            "field": "id",
            "header": "Sr.No",
            "iseditable": false,
            "class": ""
        },
        {
            "field": "mstLabel",
            "header": "MstrModule",
            "iseditable": false,
            "class": ""
        },
        {
            "field": "groupLabel",
            "header": "GrpModule",
            "iseditable": false,
            "class": ""
        },
        {
            "field": "label",
            "header": "SubModule",
            "iseditable": false,
            "class": ""
        },
        {
            "field": "icon",
            "header": "Icon",
            "iseditable": false,
            "class": ""
        },
        {
            "field": "routerLink",
            "header": "RouterLink",
            "iseditable": false,
            "class": ""
        },
        {
            "field": "SubModuleSequence",
            "header": "Sequence",
            "iseditable": false,
            "class": ""
        }
    ],
    "globalFilter": [
        "mstLabel",
        "icon",
        "label",
        "routerLink",
        "SubModuleSequence",
        "groupLabel"
    ],
    "rows": 10,
    "showCurrentPageReport": true,
    "rowsPerPageOptions": [
        10,
        25,
        50
    ],
    "paginator": true,
    "rowHover": true,
    "loading": false,
    "stripped": "p-datatable-striped p-datatable-sm p-datatable-gridlines",
    "isCheckbox": true,
    "isRadioButton":false,
    "resizableColumns": true,
    "isDragAndDrop":true,
    "isActions": [
        "Edit",
        "Delete",
        "isActive"
    ],
    "editicon": "../../../assets/icons/Group 1823.png",
    "expand":false,
    "buttonlbl":"",
    "textLength": 16,
    "sidebar":"p-sidebar-sm",
    "bulkAction":["Multiselect","Search","Addbutton","PDF","EXCEL","Delete"]   
}